Week3/Full_Adder/fa.v
module fulladder (
    input wire a, b, cin,
    output wire sum, cout
);

    wire [4:0] t;

    xor x0 (t[0], a, b); 
    xor x1 (sum, t[0], cin); 

    and a0 (t[1], a, b); 
    and a1 (t[2], a, cin); 
    and a2 (t[3], b, cin); 

    or o0 (t[4], t[1], t[2]); 
    or o1 (cout, t[4], t[3]); 
endmodule

Week3/Full_Adder/fatb.v
module fulladder_tb; 
    reg aa, bb, cc; 
    wire ss, cy; 
    fulladder add1 ( .a(aa), .b(bb), .cin(cc), .sum(ss), .cout(cy) ); 
    initial begin
        #0 aa = 1'b0; bb = 1'b0; cc = 1'b0; 
        #5 aa = 1'b0; bb = 1'b0; cc = 1'b1; 
        #5 aa = 1'b0; bb = 1'b0; cc = 1'b1;
        #5 aa = 1'b0; bb = 1'b1; cc = 1'b0; 
        #5 aa = 1'b0; bb = 1'b1; cc = 1'b1; 
        #5 aa = 1'b1; bb = 1'b0; cc = 1'b0; 
        #5 aa = 1'b1; bb = 1'b0; cc = 1'b1; 
        #5 aa = 1'b1; bb = 1'b1; cc = 1'b0; 
        #5 aa = 1'b1; bb = 1'b1; cc = 1'b1; 
    end
    initial begin 
        $monitor($time, "a=%b, b= %b, c= %b,sum= %b,carry= %b", aa, bb, cc, ss, cy); 
    end 
    initial begin 
        $dumpfile("fulladder.vcd"); 
        $dumpvars(0, fulladder_tb); 
    end 
endmodule

Week3/Full_Adder/fulladder.vcd
$date
	Fri Aug 25 10:55:02 2023
$end
$version
	Icarus Verilog
$end
$timescale
	1s
$end
$scope module fulladder_tb $end
$var wire 1 ! ss $end
$var wire 1 " cy $end
$var reg 1 # aa $end
$var reg 1 $ bb $end
$var reg 1 % cc $end
$scope module add1 $end
$var wire 1 # a $end
$var wire 1 $ b $end
$var wire 1 % cin $end
$var wire 1 " cout $end
$var wire 1 ! sum $end
$var wire 5 & t [4:0] $end
$upscope $end
$upscope $end
$enddefinitions $end
$comment Show the parameter values. $end
$dumpall
$end
#0
$dumpvars
b0 &
0%
0$
0#
0"
0!
$end
#5
1!
1%
#15
1!
b1 &
0%
1$
#20
1"
0!
b1001 &
1%
#25
0"
1!
b1 &
0%
0$
1#
#30
1"
0!
b10101 &
1%
#35
0!
b10010 &
0%
1$
#40
1!
b11110 &
1%
