Week3/Mux_21/mux21.v
module mux2 (
    input wire i0, i1, j, 
    output wire o
);  
assign o = (j == 0) ? i0 : i1;

endmodule

Week3/Mux_21/mux21tb.v
module TB;
    reg A, B, S;
    wire X;
    mux2 newMUX(.i0(A), .i1(B), .j(S), .o(X));
    
    initial begin
        S = 1'b0; A = 1'b0; B = 1'b0;
        #5 S = 1'b0; A = 1'b0; B = 1'b1;
        #5 S = 1'b0; A = 1'b1; B = 1'b0;
        #5 S = 1'b0; A = 1'b1; B = 1'b1;
        #5 S = 1'b1; A = 1'b0; B = 1'b0;
        #5 S = 1'b1; A = 1'b0; B = 1'b1;
        #5 S = 1'b1; A = 1'b1; B = 1'b0;
        #5 S = 1'b1; A = 1'b1; B = 1'b1;
    end
    initial begin 
        $monitor("Time = %0t: A = %b, B = %b, S = %b, X = %b", $time, A, B, S, X);
    end
    initial begin
        $dumpfile("MUX2_test.vcd");
        $dumpvars(0,TB);
    end
endmodule

Week3/Mux_21/MUX2_test.vcd
$date
	Fri Aug 25 18:50:41 2023
$end
$version
	Icarus Verilog
$end
$timescale
	1s
$end
$scope module TB $end
$var wire 1 ! X $end
$var reg 1 " A $end
$var reg 1 # B $end
$var reg 1 $ S $end
$scope module newMUX $end
$var wire 1 " i0 $end
$var wire 1 # i1 $end
$var wire 1 $ j $end
$var wire 1 ! o $end
$upscope $end
$upscope $end
$enddefinitions $end
$comment Show the parameter values. $end
$dumpall
$end
#0
$dumpvars
0$
0#
0"
0!
$end
#5
1#
#10
1!
0#
1"
#15
1#
#20
0!
0#
0"
1$
#25
1!
1#
#30
0!
0#
1"
#35
1!
1#
